uvalde/__init__.py
uvalde/config_commands.py
uvalde/configuration.py
uvalde/database.py
uvalde/import_command.py
uvalde/list_commands.py
uvalde/move_command.py
uvalde/remove_command.py
uvalde/repodata.py
uvalde/transfer.py
uvalde-0.3.0.dist-info/LICENSE
uvalde-0.3.0.dist-info/METADATA
uvalde-0.3.0.dist-info/WHEEL
uvalde-0.3.0.dist-info/entry_points.txt
uvalde-0.3.0.dist-info/top_level.txt
uvalde-0.3.0.dist-info/RECORD
