Metadata-Version: 2.1
Name: uvalde
Version: 0.3.0
Summary: Yum repository management tool
Home-page: https://github.com/carlwgeorge/uvalde
Author: Carl George
Author-email: carl@george.computer
License: MIT
Platform: UNKNOWN
Classifier: License :: OSI Approved :: MIT License
Classifier: Operating System :: POSIX :: Linux
Classifier: Programming Language :: Python :: 3 :: Only
Classifier: Topic :: System :: Archiving :: Packaging
Classifier: Topic :: System :: Software Distribution
Requires-Python: >=3.6
Requires-Dist: appdirs
Requires-Dist: click
Requires-Dist: createrepo-c
Requires-Dist: peewee
Provides-Extra: tests
Requires-Dist: pytest ; extra == 'tests'
Requires-Dist: pytest-cov ; extra == 'tests'
Requires-Dist: pytest-flake8 ; extra == 'tests'
Requires-Dist: repomd ; extra == 'tests'
